edwh_auth_rbac/__init__.py
edwh_auth_rbac/helpers.py
edwh_auth_rbac/migrations.py
edwh_auth_rbac/model.py
edwh_auth_rbac/rbac.py
edwh_auth_rbac-1.0.2.dist-info/METADATA
edwh_auth_rbac-1.0.2.dist-info/WHEEL
edwh_auth_rbac-1.0.2.dist-info/RECORD
