Metadata-Version: 2.4
Name: edwh-auth-rbac
Version: 1.0.2
Summary: Recursive Memberships and Permissions for the Education Warehouse Authentication System
Project-URL: Documentation, https://github.com/educationwarehouse/edwh-auth-rbac#readme
Project-URL: Issues, https://github.com/educationwarehouse/edwh-auth-rbac/issues
Project-URL: Source, https://github.com/educationwarehouse/edwh-auth-rbac
Author-email: Remco Boerma <remco.b@educationwarehouse.nl>, Robin van der Noord <robin.vdn@educationwarehouse.nl>
License-Expression: MIT
Keywords: edwh,omgeving,whitelabel
Classifier: Development Status :: 4 - Beta
Classifier: Programming Language :: Python :: 3.10
Classifier: Programming Language :: Python :: 3.11
Classifier: Programming Language :: Python :: 3.12
Requires-Python: >=3.10
Requires-Dist: dotmap
Requires-Dist: edwh-migrate
Requires-Dist: pydal
Requires-Dist: python-dateutil
Provides-Extra: dev
Requires-Dist: edwh; extra == 'dev'
Requires-Dist: edwh-migrate; extra == 'dev'
Requires-Dist: hatch; extra == 'dev'
Requires-Dist: psycopg2-binary; extra == 'dev'
Requires-Dist: python-semantic-release<8; extra == 'dev'
Requires-Dist: requests<2.32; extra == 'dev'
Requires-Dist: su6[all]; extra == 'dev'
Requires-Dist: testcontainers; extra == 'dev'
